{"data_mtime":1699099340,"dep_lines":[3,4,5,6,7,1,2,8,17,1,9,10,11,12,13,14,15,16],"dep_prios":[5,5,5,5,5,5,5,5,5,5,5,5,5,5,5,5,5,5],"dependencies":["maxgradient.color","maxgradient.gradient","maxgradient.highlighter","maxgradient.rule","maxgradient.theme","_typeshed","datetime","pathlib","typing","builtins"],"hash":"82adf7bf19d133dbe8dd14778f91d19fea40b721458a393067a2cc11ab7b7ad8","id":"maxgradient._console","ignore_all":false,"interface_hash":"e85a82f8c8bff44d4880ecc0d21085bc854cf32363c90cacbd4143a2d4132235","mtime":1699098856,"options":{"allow_redefinition":false,"allow_untyped_globals":false,"always_false":[],"always_true":[],"bazel":false,"check_untyped_defs":false,"disable_bytearray_promotion":false,"disable_error_code":[],"disable_memoryview_promotion":false,"disabled_error_codes":[],"disallow_any_decorated":false,"disallow_any_explicit":false,"disallow_any_expr":false,"disallow_any_generics":false,"disallow_any_unimported":false,"disallow_incomplete_defs":false,"disallow_subclassing_any":false,"disallow_untyped_calls":false,"disallow_untyped_decorators":false,"disallow_untyped_defs":false,"enable_error_code":[],"enabled_error_codes":[],"extra_checks":false,"follow_imports":"skip","follow_imports_for_stubs":false,"ignore_errors":true,"ignore_missing_imports":false,"implicit_optional":false,"implicit_reexport":true,"local_partial_types":false,"mypyc":false,"new_type_inference":false,"platform":"darwin","plugins":[],"strict_concatenate":false,"strict_equality":false,"strict_optional":true,"warn_no_return":true,"warn_return_any":false,"warn_unreachable":false,"warn_unused_ignores":false},"path":"./_console.pyi","plugin_data":null,"size":3370,"suppressed":["rich._log_render","rich.align","rich.console","rich.emoji","rich.style","rich.terminal_theme","rich.text","rich.theme"],"version_id":"1.6.1"}